blackjack/__init__.py
blackjack/app.py
blackjack/util.py
blackjack/assets/0cardback.png
blackjack/assets/0cardfront.png
blackjack/assets/chip.png
blackjack/cards_png/10_of_clubs.png
blackjack/cards_png/10_of_diamonds.png
blackjack/cards_png/10_of_hearts.png
blackjack/cards_png/10_of_spades.png
blackjack/cards_png/2_of_clubs.png
blackjack/cards_png/2_of_diamonds.png
blackjack/cards_png/2_of_hearts.png
blackjack/cards_png/2_of_spades.png
blackjack/cards_png/3_of_clubs.png
blackjack/cards_png/3_of_diamonds.png
blackjack/cards_png/3_of_hearts.png
blackjack/cards_png/3_of_spades.png
blackjack/cards_png/4_of_clubs.png
blackjack/cards_png/4_of_diamonds.png
blackjack/cards_png/4_of_hearts.png
blackjack/cards_png/4_of_spades.png
blackjack/cards_png/5_of_clubs.png
blackjack/cards_png/5_of_diamonds.png
blackjack/cards_png/5_of_hearts.png
blackjack/cards_png/5_of_spades.png
blackjack/cards_png/6_of_clubs.png
blackjack/cards_png/6_of_diamonds.png
blackjack/cards_png/6_of_hearts.png
blackjack/cards_png/6_of_spades.png
blackjack/cards_png/7_of_clubs.png
blackjack/cards_png/7_of_diamonds.png
blackjack/cards_png/7_of_hearts.png
blackjack/cards_png/7_of_spades.png
blackjack/cards_png/8_of_clubs.png
blackjack/cards_png/8_of_diamonds.png
blackjack/cards_png/8_of_hearts.png
blackjack/cards_png/8_of_spades.png
blackjack/cards_png/9_of_clubs.png
blackjack/cards_png/9_of_diamonds.png
blackjack/cards_png/9_of_hearts.png
blackjack/cards_png/9_of_spades.png
blackjack/cards_png/ace_of_clubs.png
blackjack/cards_png/ace_of_diamonds.png
blackjack/cards_png/ace_of_hearts.png
blackjack/cards_png/ace_of_spades.png
blackjack/cards_png/jack_of_clubs.png
blackjack/cards_png/jack_of_diamonds.png
blackjack/cards_png/jack_of_hearts.png
blackjack/cards_png/jack_of_spades.png
blackjack/cards_png/king_of_clubs.png
blackjack/cards_png/king_of_diamonds.png
blackjack/cards_png/king_of_hearts.png
blackjack/cards_png/king_of_spades.png
blackjack/cards_png/queen_of_clubs.png
blackjack_amiyuki-0.1.1.dist-info/LICENSE
blackjack_amiyuki-0.1.1.dist-info/WHEEL
blackjack_amiyuki-0.1.1.dist-info/METADATA
blackjack_amiyuki-0.1.1.dist-info/RECORD
